{"players": [[3, 5], [0, 0], [0, 0], [0, 0], [0, 0]], "humanPath": [[3, 0], [3, 1], [3, 2], [3, 3], [3, 4], [3, 5], [3, 6]], "comm": null, "message": {"1": {}, "2": {}, "3": {}, "4": {}}, "contains_action": true, "otherPaths": [[[3, 0], [3, 1], [3, 2], [3, 3], [3, 4], [3, 5], [3, 6]], [[0, 3], [1, 3], [2, 3], [3, 3], [4, 3], [5, 3], [6, 3]], 0, 0], "moveRT": [5.242041826248169, 0.17885684967041016, 0.19728708267211914, 0.19814801216125488, 0.21377301216125488, 0.20500516891479492], "step": 5, "best": 6, "done": false, "results": "other", "collisionLocation": [], "currentTrial": 10, "history": [[[3, 0], [3, 5], [2, 3], [0, 0], [0, 0]], [[3, 1], [3, 6], [3, 3], [0, 0], [0, 0]], [[3, 2], [0, 0], [4, 3], [0, 0], [0, 0]], [[3, 3], [0, 0], [5, 3], [0, 0], [0, 0]], [[3, 4], [0, 0], [6, 3], [0, 0], [0, 0]], [[3, 5], [0, 0], [0, 0], [0, 0], [0, 0]]], "actionList": [1, 1, 1, 1, 1, 1], "condition": 0}